Metadata-Version: 2.1
Name: azmonitor
Version: 0.8.1
Summary: It is a helper tool for azure monitor. It is not official.
Home-page: https://github.com/KentaroAOKI/azmonitor
Author: Kentaro Aoki
License: UNKNOWN
Keywords: azmonitor
Platform: UNKNOWN
Classifier: License :: OSI Approved :: Apache Software License
Classifier: Programming Language :: Python :: 3.4
Classifier: Programming Language :: Python :: 3.5
Classifier: Programming Language :: Python :: 3.6
Classifier: Programming Language :: Python :: 3.7
